wechatpy_ext/__init__.py
wechatpy_ext/client/__init__.py
wechatpy_ext/client/jsapi.py
wechatpy_ext/pay/__init__.py
wechatpy_ext/pay/refund.py
WeChatPy_Ext-0.1.dist-info/LICENSE
WeChatPy_Ext-0.1.dist-info/METADATA
WeChatPy_Ext-0.1.dist-info/WHEEL
WeChatPy_Ext-0.1.dist-info/top_level.txt
WeChatPy_Ext-0.1.dist-info/RECORD
